whitebeam/__init__.py
whitebeam/base/__init__.py
whitebeam/base/c45.py
whitebeam/base/cart.py
whitebeam/base/ccp.py
whitebeam/base/friedman.py
whitebeam/base/regr.py
whitebeam/base/xgb.py
whitebeam/core/__init__.py
whitebeam/core/_whitebeam.c
whitebeam/core/_whitebeam.pyx
whitebeam/core/lib.py
whitebeam/ensemble/__init__.py
whitebeam/ensemble/randomforest.py
whitebeam/ensemble/sgtb.py
whitebeam/utils/__init__.py
whitebeam/utils/util.py
whtitebeam/core/_whitebeam.cpython-38-x86_64-linux-gnu.so
whtitebeam/core/_whitebeam/c.cpython-38-x86_64-linux-gnu.so
test/utils.py
test/test_base.py
test/__init__.py
test/test_parrelisation.py
whitebeam/ensemble/paloboost.py
whitebeam/base/alpha.py
whitebeam/base/gini.py
whitebeam/core/_whitebeam.cpython-38-x86_64-linux-gnu.so
whitebeam-1.1.dist-info/WHEEL
whitebeam-1.1.dist-info/METADATA
whitebeam-1.1.dist-info/RECORD
