Metadata-Version: 2.1
Name: whitebeam
Version: 1.1
Summary: Whitebeam is a framework for creating decision tree functions.
Home-page: https://github.com/K-Molloy/whitebeam
Keywords: Decision Tree,Classifier,Classification,Regression
Author: K-Molloy
Author-email: kieran.b.molloy@outlook.com
Requires-Python: >=3.7,<4.0
Classifier: Development Status :: 2 - Pre-Alpha
Classifier: Intended Audience :: Education
Classifier: License :: Free For Educational Use
Classifier: Operating System :: Unix
Classifier: Programming Language :: Python :: 3
Classifier: Programming Language :: Python :: 3.7
Classifier: Programming Language :: Python :: 3.8
Classifier: Programming Language :: Python :: 3.9
Classifier: Topic :: Scientific/Engineering
Requires-Dist: Cython (>=0.29.21,<0.30.0)
Requires-Dist: joblib (>=1.0.0,<2.0.0)
Requires-Dist: numpy (>=1.19.5,<2.0.0)
Project-URL: Repository, https://github.com/K-Molloy/whitebeam
